jsmapper/types.py
jsmapper/schema.py
jsmapper/mapping.py
jsmapper/exceptions.py
jsmapper/__init__.py
jsmapper/defines.py
jsmapper/tests/test_mapping.py
jsmapper/tests/test_types.py
jsmapper/tests/__init__.py
jsmapper/tests/test_schema.py
jsmapper-0.1.9.dist-info/METADATA
jsmapper-0.1.9.dist-info/RECORD
jsmapper-0.1.9.dist-info/WHEEL
jsmapper-0.1.9.dist-info/top_level.txt
jsmapper-0.1.9.dist-info/DESCRIPTION.rst
jsmapper-0.1.9.dist-info/metadata.json
