Metadata-Version: 2.0
Name: jsmapper
Version: 0.1.9
Summary: A Object - JSON Schema Mapper.
Home-page: https://github.com/yosida95/python-jsmapper
Author: Kohei YOSHIDA
Author-email: license@yosida95.com
License: The MIT License (MIT) Copyright © 2014 Kohei YOSHIDA <license@yosida95.com>
Requires-Dist: jsonschema (==2.4.0)
